pytorch_molecular_energy/__init__.py
pytorch_molecular_energy/rdkit_energy.py
pytorch_molecular_energy-0.1.2.dist-info/METADATA
pytorch_molecular_energy-0.1.2.dist-info/WHEEL
pytorch_molecular_energy-0.1.2.dist-info/RECORD
